categories/__init__.py
categories/plugin.py
mkdocs_categories_plugin-0.5.0.dist-info/LICENSE.md
mkdocs_categories_plugin-0.5.0.dist-info/METADATA
mkdocs_categories_plugin-0.5.0.dist-info/WHEEL
mkdocs_categories_plugin-0.5.0.dist-info/entry_points.txt
mkdocs_categories_plugin-0.5.0.dist-info/top_level.txt
mkdocs_categories_plugin-0.5.0.dist-info/RECORD
