Metadata-Version: 2.1
Name: mkdocs-categories-plugin
Version: 0.5.0
Summary: An MkDocs plugin allowing for categorization of pages
Home-page: https://github.com/eddyluten/mkdocs-categories-plugin
Author: Eddy Luten
Author-email: eddyluten@gmail.com
License: MIT
Keywords: mkdocs python markdown category categories link wiki
Classifier: License :: OSI Approved :: MIT License
Classifier: Programming Language :: Python
Classifier: Programming Language :: Python :: 3 :: Only
Classifier: Topic :: Software Development :: Libraries :: Python Modules
Requires-Python: >=3.10
License-File: LICENSE.md
Requires-Dist: mkdocs
Requires-Dist: natsort >=8.4.0
